AUTHORS.rst
CONTRIBUTING.rst
LICENSE
MANIFEST.in
README.md
README.rst
setup.py
docs/Makefile
docs/authors.rst
docs/conf.py
docs/contributing.rst
docs/history.rst
docs/index.rst
docs/installation.rst
docs/make.bat
docs/readme.rst
docs/usage.rst
docs/imgs/pistis_gc_plot.png
docs/imgs/pistis_perc_id.png
docs/imgs/pistis_qual_end.png
docs/imgs/pistis_qual_start.png
docs/imgs/pistis_qual_v_len.png
pistis/__init__.py
pistis/pistis.py
pistis/plots.py
pistis/utils.py
pistis.egg-info/PKG-INFO
pistis.egg-info/SOURCES.txt
pistis.egg-info/dependency_links.txt
pistis.egg-info/entry_points.txt
pistis.egg-info/not-zip-safe
pistis.egg-info/requires.txt
pistis.egg-info/top_level.txt
tests/test_pistis.py
tests/test_plots.py
tests/test_utils.py
tests/data/alignment.bam
tests/data/alignment.bam.bai
tests/data/reads.fastq.gz
tests/images/gc_plot-expected.png
tests/images/len_v_qual-expected.png
tests/images/percent_identity-expected.png
tests/images/qual_pos_end-expected.png
tests/images/qual_pos_start-expected.png
tests/images/report-expected.pdf