Metadata-Version: 2.1
Name: pistis
Version: 0.3.4
Summary: Quality control plotting for long reads
Home-page: https://github.com/mbhall88/pistis
Author: Michael Benjamin Hall
Author-email: mbhall88@gmail.com
License: MIT license
Keywords: pistis
Platform: UNKNOWN
Classifier: Development Status :: 2 - Pre-Alpha
Classifier: Intended Audience :: Developers
Classifier: License :: OSI Approved :: MIT License
Classifier: Natural Language :: English
Classifier: Programming Language :: Python :: 3.6
